{
  "project_info": {
    "project_number": "919624159945",
    "project_id": "minote-app",
    "storage_bucket": "minote-app.appspot.com"
  },
  "client": [
    {
      "client_info": {
        "mobilesdk_app_id": "1:919624159945:android:7f9c0487ae606dd8277318",
        "android_client_info": {
          "package_name": "com.wnr.minotes"
        }
      },
      "oauth_client": [
        {
          "client_id": "919624159945-bka3kdfntaqtmi9dv4mhrlm4lvr80bon.apps.googleusercontent.com",
          "client_type": 1,
          "android_info": {
            "package_name": "com.wnr.minotes",
            "certificate_hash": "5e8f16062ea3cd2c4a0d547876baa6f38cabf625"
          }
        },
        {
          "client_id": "919624159945-rcke5fftkolpqcf3juabdun3b07t15p2.apps.googleusercontent.com",
          "client_type": 3
        }
      ],
      "api_key": [
        {
          "current_key": "AIzaSyDQVIhOfySPYRupnz8TZBe-fwIIOu0g4bE"
        }
      ],
      "services": {
        "appinvite_service": {
          "other_platform_oauth_client": [
            {
              "client_id": "919624159945-rcke5fftkolpqcf3juabdun3b07t15p2.apps.googleusercontent.com",
              "client_type": 3
            }
          ]
        }
      }
    }
  ],
  "configuration_version": "1"
}